djangito_client/__init__.py
djangito_client/apps.py
djangito_client/core.py
djangito_client/io.py
djangito_client/models.py
djangito_client/patches.py
djangito_client/urls.py
djangito_client/views.py
djangito_client/migrations/__init__.py
djangito_server/__init__.py
djangito_server/admin.py
djangito_server/apps.py
djangito_server/models.py
djangito_server/serializers.py
djangito_server/signals.py
djangito_server/urls.py
djangito_server/views.py
djangito_server/migrations/__init__.py
users/__init__.py
users/admin.py
users/apps.py
users/models.py
users/migrations/0001_create_custom_user.py
users/migrations/0002_create_company_model.py
users/migrations/0003_add_verbose_name_plural.py
users/migrations/0004_add_primary_activity.py
users/migrations/0005_add_server_id.py
users/migrations/__init__.py
Djangito-0.0.5.dist-info/LICENSE
Djangito-0.0.5.dist-info/METADATA
Djangito-0.0.5.dist-info/WHEEL
Djangito-0.0.5.dist-info/top_level.txt
Djangito-0.0.5.dist-info/RECORD
