Metadata-Version: 2.1
Name: Djangito
Version: 0.0.5
Summary: Enables one Django project to authenticate via a second Django project via oauth2.
Home-page: https://github.com/pandichef/djangito
Author: David R
License: UNKNOWN
Project-URL: Bug Reports, https://github.com/pandichef/djangito/issues/
Project-URL: Source, https://github.com/pandichef/djangito/
Keywords: sample setuptools development
Platform: UNKNOWN
Classifier: Development Status :: 3 - Alpha
Classifier: Intended Audience :: Developers
Classifier: Topic :: Software Development :: Build Tools
Classifier: License :: OSI Approved :: MIT License
Classifier: Programming Language :: Python :: 3.6
Classifier: Programming Language :: Python :: 3.7
Classifier: Programming Language :: Python :: 3.8
Requires-Python: >=2.7, !=3.0.*, !=3.1.*, !=3.2.*, !=3.3.*, !=3.4.*, !=3.5.*, <4
Requires-Dist: django (==2.2.13)
Requires-Dist: django-oauth-toolkit (==1.2.0)
Requires-Dist: pyjwt (==1.7.1)
Requires-Dist: djangorestframework (==3.11.0)
Provides-Extra: dev
Requires-Dist: django-debug-toolbar ; extra == 'dev'
Requires-Dist: pipenv-setup ; extra == 'dev'
Requires-Dist: ipython ; extra == 'dev'
Requires-Dist: pytest ; extra == 'dev'
Requires-Dist: pytest-cov ; extra == 'dev'
Requires-Dist: pytest-django ; extra == 'dev'
Requires-Dist: pytest-factoryboy ; extra == 'dev'
Requires-Dist: pytest-pythonpath ; extra == 'dev'
